[{"Name":"Bishkek","Description":"Bishkek (Бишкек) (population in 2009 approx. 835,000) is the capital and largest city in Kyrgyzstan.\n","Latitude":"42.874722","Longitude":"74.612222","Url":"https://en.wikivoyage.org/wiki/Bishkek","Country":"Kyrgyzstan","Photo":"https://upload.wikimedia.org/wikipedia/commons/9/9c/Bishkek_banner.jpg"},{"Name":"Balykchy","Description":"Balykchy (Балыкчы) is a city at Issyk Kul.\n","Latitude":"42.4667","Longitude":"76.1833","Url":"https://en.wikivoyage.org/wiki/Balykchy","Country":"Kyrgyzstan","Photo":"https://upload.wikimedia.org/wikipedia/commons/f/f2/Pagebanner_default.jpg"},null,{"Name":"Karakol","Description":"Karakol (Каракол) is a city in Kyrgyzstan on the east of Lake Issyk Kul.\n","Latitude":"42.4833","Longitude":"78.4000","Url":"https://en.wikivoyage.org/wiki/Karakol","Country":"Kyrgyzstan","Photo":"https://upload.wikimedia.org/wikipedia/commons/thumb/5/5d/Karakol_%28Kyrgyzstan%29_banner_Karakol_Valley.jpg/2560px-Karakol_%28Kyrgyzstan%29_banner_Karakol_Valley.jpg"},{"Name":"Kochkor","Description":"Kochkor is a town in Kyrgyzstan's Issyk-Kul and the Tian Shan region.\n","Latitude":"42.230000","Longitude":"75.750000","Url":"https://en.wikivoyage.org/wiki/Kochkor","Country":"Kyrgyzstan","Photo":"https://upload.wikimedia.org/wikipedia/commons/9/99/Kochkor_and_mountains_7-1.jpg"},{"Name":"Naryn","Description":"\n","Latitude":"41.4333","Longitude":"76.0000","Url":"https://en.wikivoyage.org/wiki/Naryn","Country":"Kyrgyzstan","Photo":"https://upload.wikimedia.org/wikipedia/commons/f/f2/Pagebanner_default.jpg"},{"Name":"Osh","Description":"Osh is a city in the Ferghana Valley of Kyrgyzstan.\n","Latitude":"40.533333333333","Longitude":"72.783333333333","Url":"https://en.wikivoyage.org/wiki/Osh","Country":"Kyrgyzstan","Photo":"https://upload.wikimedia.org/wikipedia/commons/e/e0/Osh_%28Kyrgyzstan%29_banner_Suleiman_hill.jpg"},null,null]